README.rst
pytest_rethinkdb.py
setup.py
pytest_rethinkdb.egg-info/PKG-INFO
pytest_rethinkdb.egg-info/SOURCES.txt
pytest_rethinkdb.egg-info/dependency_links.txt
pytest_rethinkdb.egg-info/entry_points.txt
pytest_rethinkdb.egg-info/requires.txt
pytest_rethinkdb.egg-info/top_level.txt